pybos/__init__.py
pybos/base_service.py
pybos/bos.py
pybos/wsdl_services.py
chq_pybos-0.1.0.dist-info/METADATA
chq_pybos-0.1.0.dist-info/WHEEL
chq_pybos-0.1.0.dist-info/top_level.txt
chq_pybos-0.1.0.dist-info/RECORD
