Metadata-Version: 2.4
Name: chq-pybos
Version: 0.1.0
Summary: A Python client library for the BOS API with improved developer ergonomics and type safety
Home-page: https://gitlab.it.chq.org/IT/pybos
Author: Jared Brown
Author-email: Jared Brown <jbrown@chq.org>, Randy Butts <rbutts@chq.org>, Ian Drake <idrake@chq.org>
License: MIT
Requires-Python: >=3.12
Requires-Dist: suds>=1.0.0
Requires-Dist: requests>=2.25.0
Requires-Dist: xmltodict>=0.12.0
Requires-Dist: pytest>=8.4.2
Provides-Extra: dev
Requires-Dist: black>=25.1.0; extra == "dev"
Requires-Dist: pytest>=8.4.2; extra == "dev"
Dynamic: author
Dynamic: home-page
